{
  "avg": [
    {
      "rank": 1,
      "name": "최원준",
      "team": "KT",
      "avg": 0.365,
      "games": 75,
      "pa": 359,
      "ab": 307,
      "hits": 112,
      "doubles": 20,
      "triples": 3,
      "hr": 7,
      "rbi": 44,
      "sb": 16,
      "bb": 41,
      "hbp": 5,
      "so": 51
    },
    {
      "rank": 2,
      "name": "이우성",
      "team": "NC",
      "avg": 0.355,
      "games": 73,
      "pa": 285,
      "ab": 265,
      "hits": 94,
      "doubles": 15,
      "triples": 0,
      "hr": 6,
      "rbi": 34,
      "sb": 4,
      "bb": 17,
      "hbp": 1,
      "so": 42
    },
    {
      "rank": 3,
      "name": "오스틴",
      "team": "LG",
      "avg": 0.351,
      "games": 79,
      "pa": 351,
      "ab": 305,
      "hits": 107,
      "doubles": 16,
      "triples": 3,
      "hr": 26,
      "rbi": 79,
      "sb": 2,
      "bb": 38,
      "hbp": 5,
      "so": 53
    },
    {
      "rank": 4,
      "name": "박민우",
      "team": "NC",
      "avg": 0.339,
      "games": 74,
      "pa": 312,
      "ab": 257,
      "hits": 87,
      "doubles": 17,
      "triples": 0,
      "hr": 4,
      "rbi": 45,
      "sb": 25,
      "bb": 45,
      "hbp": 6,
      "so": 36
    },
    {
      "rank": 5,
      "name": "레이예스",
      "team": "롯데",
      "avg": 0.338,
      "games": 78,
      "pa": 345,
      "ab": 308,
      "hits": 104,
      "doubles": 17,
      "triples": 1,
      "hr": 10,
      "rbi": 55,
      "sb": 1,
      "bb": 32,
      "hbp": 2,
      "so": 40
    },
    {
      "rank": 6,
      "name": "박성한",
      "team": "SSG",
      "avg": 0.336,
      "games": 79,
      "pa": 347,
      "ab": 289,
      "hits": 97,
      "doubles": 18,
      "triples": 1,
      "hr": 3,
      "rbi": 36,
      "sb": 5,
      "bb": 55,
      "hbp": 1,
      "so": 37
    },
    {
      "rank": 7,
      "name": "최형우",
      "team": "삼성",
      "avg": 0.327,
      "games": 75,
      "pa": 321,
      "ab": 263,
      "hits": 86,
      "doubles": 14,
      "triples": 0,
      "hr": 10,
      "rbi": 58,
      "sb": 1,
      "bb": 49,
      "hbp": 3,
      "so": 43
    },
    {
      "rank": 8,
      "name": "구자욱",
      "team": "삼성",
      "avg": 0.324,
      "games": 60,
      "pa": 258,
      "ab": 219,
      "hits": 71,
      "doubles": 14,
      "triples": 3,
      "hr": 7,
      "rbi": 50,
      "sb": 3,
      "bb": 32,
      "hbp": 3,
      "so": 37
    },
    {
      "rank": 9,
      "name": "페라자",
      "team": "한화",
      "avg": 0.315,
      "games": 77,
      "pa": 346,
      "ab": 286,
      "hits": 90,
      "doubles": 21,
      "triples": 1,
      "hr": 17,
      "rbi": 51,
      "sb": 7,
      "bb": 51,
      "hbp": 3,
      "so": 64
    },
    {
      "rank": 10,
      "name": "김민석",
      "team": "두산",
      "avg": 0.314,
      "games": 72,
      "pa": 259,
      "ab": 229,
      "hits": 72,
      "doubles": 14,
      "triples": 2,
      "hr": 4,
      "rbi": 28,
      "sb": 2,
      "bb": 27,
      "hbp": 1,
      "so": 43
    },
    {
      "rank": 11,
      "name": "김주원",
      "team": "NC",
      "avg": 0.312,
      "games": 76,
      "pa": 342,
      "ab": 298,
      "hits": 93,
      "doubles": 15,
      "triples": 0,
      "hr": 12,
      "rbi": 37,
      "sb": 20,
      "bb": 27,
      "hbp": 13,
      "so": 46
    },
    {
      "rank": 12,
      "name": "강백호",
      "team": "한화",
      "avg": 0.312,
      "games": 73,
      "pa": 320,
      "ab": 282,
      "hits": 88,
      "doubles": 17,
      "triples": 0,
      "hr": 20,
      "rbi": 79,
      "sb": 0,
      "bb": 34,
      "hbp": 1,
      "so": 66
    },
    {
      "rank": 13,
      "name": "김현수",
      "team": "KT",
      "avg": 0.304,
      "games": 76,
      "pa": 343,
      "ab": 309,
      "hits": 94,
      "doubles": 21,
      "triples": 0,
      "hr": 5,
      "rbi": 51,
      "sb": 0,
      "bb": 31,
      "hbp": 1,
      "so": 37
    },
    {
      "rank": 14,
      "name": "최정",
      "team": "SSG",
      "avg": 0.303,
      "games": 64,
      "pa": 275,
      "ab": 228,
      "hits": 69,
      "doubles": 14,
      "triples": 1,
      "hr": 18,
      "rbi": 50,
      "sb": 3,
      "bb": 36,
      "hbp": 6,
      "so": 57
    },
    {
      "rank": 15,
      "name": "힐리어드",
      "team": "KT",
      "avg": 0.298,
      "games": 77,
      "pa": 345,
      "ab": 305,
      "hits": 91,
      "doubles": 14,
      "triples": 3,
      "hr": 19,
      "rbi": 68,
      "sb": 7,
      "bb": 36,
      "hbp": 0,
      "so": 92
    },
    {
      "rank": 16,
      "name": "김지찬",
      "team": "삼성",
      "avg": 0.298,
      "games": 76,
      "pa": 290,
      "ab": 238,
      "hits": 71,
      "doubles": 5,
      "triples": 2,
      "hr": 0,
      "rbi": 21,
      "sb": 13,
      "bb": 40,
      "hbp": 3,
      "so": 18
    },
    {
      "rank": 17,
      "name": "박해민",
      "team": "LG",
      "avg": 0.296,
      "games": 79,
      "pa": 309,
      "ab": 257,
      "hits": 76,
      "doubles": 11,
      "triples": 0,
      "hr": 3,
      "rbi": 32,
      "sb": 22,
      "bb": 27,
      "hbp": 8,
      "so": 40
    },
    {
      "rank": 18,
      "name": "류지혁",
      "team": "삼성",
      "avg": 0.295,
      "games": 75,
      "pa": 296,
      "ab": 251,
      "hits": 74,
      "doubles": 12,
      "triples": 4,
      "hr": 5,
      "rbi": 42,
      "sb": 15,
      "bb": 34,
      "hbp": 6,
      "so": 44
    },
    {
      "rank": 19,
      "name": "김도영",
      "team": "KIA",
      "avg": 0.294,
      "games": 80,
      "pa": 348,
      "ab": 296,
      "hits": 87,
      "doubles": 15,
      "triples": 1,
      "hr": 25,
      "rbi": 70,
      "sb": 5,
      "bb": 44,
      "hbp": 5,
      "so": 55
    },
    {
      "rank": 20,
      "name": "김상수",
      "team": "KT",
      "avg": 0.29,
      "games": 69,
      "pa": 269,
      "ab": 224,
      "hits": 65,
      "doubles": 6,
      "triples": 1,
      "hr": 0,
      "rbi": 23,
      "sb": 0,
      "bb": 34,
      "hbp": 5,
      "so": 32
    },
    {
      "rank": 21,
      "name": "정준재",
      "team": "SSG",
      "avg": 0.29,
      "games": 76,
      "pa": 309,
      "ab": 262,
      "hits": 76,
      "doubles": 8,
      "triples": 5,
      "hr": 1,
      "rbi": 27,
      "sb": 11,
      "bb": 27,
      "hbp": 3,
      "so": 40
    },
    {
      "rank": 22,
      "name": "디아즈",
      "team": "삼성",
      "avg": 0.29,
      "games": 78,
      "pa": 350,
      "ab": 307,
      "hits": 89,
      "doubles": 16,
      "triples": 0,
      "hr": 15,
      "rbi": 68,
      "sb": 1,
      "bb": 39,
      "hbp": 1,
      "so": 56
    },
    {
      "rank": 23,
      "name": "데이비슨",
      "team": "NC",
      "avg": 0.29,
      "games": 63,
      "pa": 252,
      "ab": 221,
      "hits": 64,
      "doubles": 11,
      "triples": 1,
      "hr": 8,
      "rbi": 40,
      "sb": 1,
      "bb": 12,
      "hbp": 17,
      "so": 58
    },
    {
      "rank": 24,
      "name": "박승규",
      "team": "삼성",
      "avg": 0.287,
      "games": 63,
      "pa": 244,
      "ab": 202,
      "hits": 58,
      "doubles": 8,
      "triples": 5,
      "hr": 9,
      "rbi": 33,
      "sb": 5,
      "bb": 37,
      "hbp": 3,
      "so": 37
    },
    {
      "rank": 25,
      "name": "카메론",
      "team": "두산",
      "avg": 0.287,
      "games": 75,
      "pa": 314,
      "ab": 279,
      "hits": 80,
      "doubles": 19,
      "triples": 3,
      "hr": 9,
      "rbi": 43,
      "sb": 9,
      "bb": 30,
      "hbp": 3,
      "so": 53
    },
    {
      "rank": 26,
      "name": "박건우",
      "team": "NC",
      "avg": 0.286,
      "games": 74,
      "pa": 297,
      "ab": 252,
      "hits": 72,
      "doubles": 9,
      "triples": 0,
      "hr": 14,
      "rbi": 47,
      "sb": 5,
      "bb": 35,
      "hbp": 1,
      "so": 56
    },
    {
      "rank": 27,
      "name": "김호령",
      "team": "KIA",
      "avg": 0.286,
      "games": 79,
      "pa": 340,
      "ab": 308,
      "hits": 88,
      "doubles": 17,
      "triples": 1,
      "hr": 11,
      "rbi": 46,
      "sb": 8,
      "bb": 19,
      "hbp": 3,
      "so": 92
    },
    {
      "rank": 28,
      "name": "문현빈",
      "team": "한화",
      "avg": 0.285,
      "games": 75,
      "pa": 343,
      "ab": 295,
      "hits": 84,
      "doubles": 20,
      "triples": 4,
      "hr": 9,
      "rbi": 48,
      "sb": 5,
      "bb": 40,
      "hbp": 4,
      "so": 39
    },
    {
      "rank": 29,
      "name": "나성범",
      "team": "KIA",
      "avg": 0.285,
      "games": 76,
      "pa": 310,
      "ab": 267,
      "hits": 76,
      "doubles": 16,
      "triples": 0,
      "hr": 15,
      "rbi": 42,
      "sb": 0,
      "bb": 36,
      "hbp": 5,
      "so": 84
    },
    {
      "rank": 30,
      "name": "안치홍",
      "team": "키움",
      "avg": 0.281,
      "games": 70,
      "pa": 289,
      "ab": 256,
      "hits": 72,
      "doubles": 12,
      "triples": 0,
      "hr": 6,
      "rbi": 29,
      "sb": 0,
      "bb": 30,
      "hbp": 2,
      "so": 41
    }
  ],
  "hr": [
    {
      "rank": 1,
      "name": "오스틴",
      "team": "LG",
      "avg": 0.351,
      "games": 79,
      "pa": 351,
      "ab": 305,
      "hits": 107,
      "doubles": 16,
      "triples": 3,
      "hr": 26,
      "rbi": 79,
      "sb": 2,
      "bb": 38,
      "hbp": 5,
      "so": 53
    },
    {
      "rank": 2,
      "name": "김도영",
      "team": "KIA",
      "avg": 0.294,
      "games": 80,
      "pa": 348,
      "ab": 296,
      "hits": 87,
      "doubles": 15,
      "triples": 1,
      "hr": 25,
      "rbi": 70,
      "sb": 5,
      "bb": 44,
      "hbp": 5,
      "so": 55
    },
    {
      "rank": 3,
      "name": "강백호",
      "team": "한화",
      "avg": 0.312,
      "games": 73,
      "pa": 320,
      "ab": 282,
      "hits": 88,
      "doubles": 17,
      "triples": 0,
      "hr": 20,
      "rbi": 79,
      "sb": 0,
      "bb": 34,
      "hbp": 1,
      "so": 66
    },
    {
      "rank": 4,
      "name": "힐리어드",
      "team": "KT",
      "avg": 0.298,
      "games": 77,
      "pa": 345,
      "ab": 305,
      "hits": 91,
      "doubles": 14,
      "triples": 3,
      "hr": 19,
      "rbi": 68,
      "sb": 7,
      "bb": 36,
      "hbp": 0,
      "so": 92
    },
    {
      "rank": 5,
      "name": "최정",
      "team": "SSG",
      "avg": 0.303,
      "games": 64,
      "pa": 275,
      "ab": 228,
      "hits": 69,
      "doubles": 14,
      "triples": 1,
      "hr": 18,
      "rbi": 50,
      "sb": 3,
      "bb": 36,
      "hbp": 6,
      "so": 57
    },
    {
      "rank": 6,
      "name": "페라자",
      "team": "한화",
      "avg": 0.315,
      "games": 77,
      "pa": 346,
      "ab": 286,
      "hits": 90,
      "doubles": 21,
      "triples": 1,
      "hr": 17,
      "rbi": 51,
      "sb": 7,
      "bb": 51,
      "hbp": 3,
      "so": 64
    },
    {
      "rank": 7,
      "name": "노시환",
      "team": "한화",
      "avg": 0.264,
      "games": 70,
      "pa": 317,
      "ab": 280,
      "hits": 74,
      "doubles": 13,
      "triples": 0,
      "hr": 15,
      "rbi": 50,
      "sb": 2,
      "bb": 29,
      "hbp": 5,
      "so": 89
    },
    {
      "rank": 8,
      "name": "디아즈",
      "team": "삼성",
      "avg": 0.29,
      "games": 78,
      "pa": 350,
      "ab": 307,
      "hits": 89,
      "doubles": 16,
      "triples": 0,
      "hr": 15,
      "rbi": 68,
      "sb": 1,
      "bb": 39,
      "hbp": 1,
      "so": 56
    },
    {
      "rank": 9,
      "name": "나성범",
      "team": "KIA",
      "avg": 0.285,
      "games": 76,
      "pa": 310,
      "ab": 267,
      "hits": 76,
      "doubles": 16,
      "triples": 0,
      "hr": 15,
      "rbi": 42,
      "sb": 0,
      "bb": 36,
      "hbp": 5,
      "so": 84
    },
    {
      "rank": 10,
      "name": "에레디아",
      "team": "SSG",
      "avg": 0.279,
      "games": 79,
      "pa": 345,
      "ab": 312,
      "hits": 87,
      "doubles": 13,
      "triples": 0,
      "hr": 14,
      "rbi": 66,
      "sb": 1,
      "bb": 22,
      "hbp": 7,
      "so": 55
    },
    {
      "rank": 11,
      "name": "박건우",
      "team": "NC",
      "avg": 0.286,
      "games": 74,
      "pa": 297,
      "ab": 252,
      "hits": 72,
      "doubles": 9,
      "triples": 0,
      "hr": 14,
      "rbi": 47,
      "sb": 5,
      "bb": 35,
      "hbp": 1,
      "so": 56
    },
    {
      "rank": 12,
      "name": "김재환",
      "team": "SSG",
      "avg": 0.22,
      "games": 69,
      "pa": 281,
      "ab": 232,
      "hits": 51,
      "doubles": 5,
      "triples": 0,
      "hr": 13,
      "rbi": 41,
      "sb": 1,
      "bb": 45,
      "hbp": 3,
      "so": 79
    },
    {
      "rank": 13,
      "name": "김주원",
      "team": "NC",
      "avg": 0.312,
      "games": 76,
      "pa": 342,
      "ab": 298,
      "hits": 93,
      "doubles": 15,
      "triples": 0,
      "hr": 12,
      "rbi": 37,
      "sb": 20,
      "bb": 27,
      "hbp": 13,
      "so": 46
    },
    {
      "rank": 14,
      "name": "허인서",
      "team": "한화",
      "avg": 0.281,
      "games": 68,
      "pa": 223,
      "ab": 192,
      "hits": 54,
      "doubles": 4,
      "triples": 0,
      "hr": 11,
      "rbi": 40,
      "sb": 0,
      "bb": 21,
      "hbp": 5,
      "so": 67
    },
    {
      "rank": 15,
      "name": "김호령",
      "team": "KIA",
      "avg": 0.286,
      "games": 79,
      "pa": 340,
      "ab": 308,
      "hits": 88,
      "doubles": 17,
      "triples": 1,
      "hr": 11,
      "rbi": 46,
      "sb": 8,
      "bb": 19,
      "hbp": 3,
      "so": 92
    },
    {
      "rank": 16,
      "name": "양의지",
      "team": "두산",
      "avg": 0.256,
      "games": 77,
      "pa": 303,
      "ab": 258,
      "hits": 66,
      "doubles": 8,
      "triples": 0,
      "hr": 11,
      "rbi": 39,
      "sb": 1,
      "bb": 23,
      "hbp": 15,
      "so": 33
    },
    {
      "rank": 17,
      "name": "최형우",
      "team": "삼성",
      "avg": 0.327,
      "games": 75,
      "pa": 321,
      "ab": 263,
      "hits": 86,
      "doubles": 14,
      "triples": 0,
      "hr": 10,
      "rbi": 58,
      "sb": 1,
      "bb": 49,
      "hbp": 3,
      "so": 43
    },
    {
      "rank": 18,
      "name": "레이예스",
      "team": "롯데",
      "avg": 0.338,
      "games": 78,
      "pa": 345,
      "ab": 308,
      "hits": 104,
      "doubles": 17,
      "triples": 1,
      "hr": 10,
      "rbi": 55,
      "sb": 1,
      "bb": 32,
      "hbp": 2,
      "so": 40
    },
    {
      "rank": 19,
      "name": "아데를린",
      "team": "KIA",
      "avg": 0.264,
      "games": 32,
      "pa": 130,
      "ab": 121,
      "hits": 32,
      "doubles": 5,
      "triples": 0,
      "hr": 10,
      "rbi": 31,
      "sb": 0,
      "bb": 7,
      "hbp": 1,
      "so": 25
    },
    {
      "rank": 20,
      "name": "문현빈",
      "team": "한화",
      "avg": 0.285,
      "games": 75,
      "pa": 343,
      "ab": 295,
      "hits": 84,
      "doubles": 20,
      "triples": 4,
      "hr": 9,
      "rbi": 48,
      "sb": 5,
      "bb": 40,
      "hbp": 4,
      "so": 39
    },
    {
      "rank": 21,
      "name": "오태곤",
      "team": "SSG",
      "avg": 0.23,
      "games": 69,
      "pa": 205,
      "ab": 187,
      "hits": 43,
      "doubles": 6,
      "triples": 0,
      "hr": 9,
      "rbi": 27,
      "sb": 6,
      "bb": 14,
      "hbp": 2,
      "so": 59
    },
    {
      "rank": 22,
      "name": "최지훈",
      "team": "SSG",
      "avg": 0.231,
      "games": 77,
      "pa": 319,
      "ab": 290,
      "hits": 67,
      "doubles": 15,
      "triples": 6,
      "hr": 9,
      "rbi": 37,
      "sb": 8,
      "bb": 21,
      "hbp": 2,
      "so": 44
    },
    {
      "rank": 23,
      "name": "박승규",
      "team": "삼성",
      "avg": 0.287,
      "games": 63,
      "pa": 244,
      "ab": 202,
      "hits": 58,
      "doubles": 8,
      "triples": 5,
      "hr": 9,
      "rbi": 33,
      "sb": 5,
      "bb": 37,
      "hbp": 3,
      "so": 37
    },
    {
      "rank": 24,
      "name": "박준순",
      "team": "두산",
      "avg": 0.33,
      "games": 47,
      "pa": 203,
      "ab": 188,
      "hits": 62,
      "doubles": 8,
      "triples": 4,
      "hr": 9,
      "rbi": 33,
      "sb": 1,
      "bb": 11,
      "hbp": 4,
      "so": 41
    },
    {
      "rank": 25,
      "name": "카메론",
      "team": "두산",
      "avg": 0.287,
      "games": 75,
      "pa": 314,
      "ab": 279,
      "hits": 80,
      "doubles": 19,
      "triples": 3,
      "hr": 9,
      "rbi": 43,
      "sb": 9,
      "bb": 30,
      "hbp": 3,
      "so": 53
    },
    {
      "rank": 26,
      "name": "박동원",
      "team": "LG",
      "avg": 0.231,
      "games": 71,
      "pa": 246,
      "ab": 199,
      "hits": 46,
      "doubles": 10,
      "triples": 0,
      "hr": 8,
      "rbi": 33,
      "sb": 1,
      "bb": 36,
      "hbp": 3,
      "so": 62
    },
    {
      "rank": 27,
      "name": "송찬의",
      "team": "LG",
      "avg": 0.294,
      "games": 57,
      "pa": 199,
      "ab": 170,
      "hits": 50,
      "doubles": 16,
      "triples": 1,
      "hr": 8,
      "rbi": 31,
      "sb": 1,
      "bb": 19,
      "hbp": 10,
      "so": 48
    },
    {
      "rank": 28,
      "name": "이재현",
      "team": "삼성",
      "avg": 0.243,
      "games": 38,
      "pa": 135,
      "ab": 111,
      "hits": 27,
      "doubles": 3,
      "triples": 0,
      "hr": 8,
      "rbi": 21,
      "sb": 0,
      "bb": 18,
      "hbp": 2,
      "so": 17
    },
    {
      "rank": 29,
      "name": "데이비슨",
      "team": "NC",
      "avg": 0.29,
      "games": 63,
      "pa": 252,
      "ab": 221,
      "hits": 64,
      "doubles": 11,
      "triples": 1,
      "hr": 8,
      "rbi": 40,
      "sb": 1,
      "bb": 12,
      "hbp": 17,
      "so": 58
    },
    {
      "rank": 30,
      "name": "장성우",
      "team": "KT",
      "avg": 0.205,
      "games": 52,
      "pa": 201,
      "ab": 161,
      "hits": 33,
      "doubles": 10,
      "triples": 0,
      "hr": 8,
      "rbi": 35,
      "sb": 1,
      "bb": 37,
      "hbp": 2,
      "so": 49
    }
  ],
  "rbi": [
    {
      "rank": 1,
      "name": "오스틴",
      "team": "LG",
      "avg": 0.351,
      "games": 79,
      "pa": 351,
      "ab": 305,
      "hits": 107,
      "doubles": 16,
      "triples": 3,
      "hr": 26,
      "rbi": 79,
      "sb": 2,
      "bb": 38,
      "hbp": 5,
      "so": 53
    },
    {
      "rank": 2,
      "name": "강백호",
      "team": "한화",
      "avg": 0.312,
      "games": 73,
      "pa": 320,
      "ab": 282,
      "hits": 88,
      "doubles": 17,
      "triples": 0,
      "hr": 20,
      "rbi": 79,
      "sb": 0,
      "bb": 34,
      "hbp": 1,
      "so": 66
    },
    {
      "rank": 3,
      "name": "김도영",
      "team": "KIA",
      "avg": 0.294,
      "games": 80,
      "pa": 348,
      "ab": 296,
      "hits": 87,
      "doubles": 15,
      "triples": 1,
      "hr": 25,
      "rbi": 70,
      "sb": 5,
      "bb": 44,
      "hbp": 5,
      "so": 55
    },
    {
      "rank": 4,
      "name": "디아즈",
      "team": "삼성",
      "avg": 0.29,
      "games": 78,
      "pa": 350,
      "ab": 307,
      "hits": 89,
      "doubles": 16,
      "triples": 0,
      "hr": 15,
      "rbi": 68,
      "sb": 1,
      "bb": 39,
      "hbp": 1,
      "so": 56
    },
    {
      "rank": 5,
      "name": "힐리어드",
      "team": "KT",
      "avg": 0.298,
      "games": 77,
      "pa": 345,
      "ab": 305,
      "hits": 91,
      "doubles": 14,
      "triples": 3,
      "hr": 19,
      "rbi": 68,
      "sb": 7,
      "bb": 36,
      "hbp": 0,
      "so": 92
    },
    {
      "rank": 6,
      "name": "에레디아",
      "team": "SSG",
      "avg": 0.279,
      "games": 79,
      "pa": 345,
      "ab": 312,
      "hits": 87,
      "doubles": 13,
      "triples": 0,
      "hr": 14,
      "rbi": 66,
      "sb": 1,
      "bb": 22,
      "hbp": 7,
      "so": 55
    },
    {
      "rank": 7,
      "name": "최형우",
      "team": "삼성",
      "avg": 0.327,
      "games": 75,
      "pa": 321,
      "ab": 263,
      "hits": 86,
      "doubles": 14,
      "triples": 0,
      "hr": 10,
      "rbi": 58,
      "sb": 1,
      "bb": 49,
      "hbp": 3,
      "so": 43
    },
    {
      "rank": 8,
      "name": "레이예스",
      "team": "롯데",
      "avg": 0.338,
      "games": 78,
      "pa": 345,
      "ab": 308,
      "hits": 104,
      "doubles": 17,
      "triples": 1,
      "hr": 10,
      "rbi": 55,
      "sb": 1,
      "bb": 32,
      "hbp": 2,
      "so": 40
    },
    {
      "rank": 9,
      "name": "페라자",
      "team": "한화",
      "avg": 0.315,
      "games": 77,
      "pa": 346,
      "ab": 286,
      "hits": 90,
      "doubles": 21,
      "triples": 1,
      "hr": 17,
      "rbi": 51,
      "sb": 7,
      "bb": 51,
      "hbp": 3,
      "so": 64
    },
    {
      "rank": 10,
      "name": "김현수",
      "team": "KT",
      "avg": 0.304,
      "games": 76,
      "pa": 343,
      "ab": 309,
      "hits": 94,
      "doubles": 21,
      "triples": 0,
      "hr": 5,
      "rbi": 51,
      "sb": 0,
      "bb": 31,
      "hbp": 1,
      "so": 37
    },
    {
      "rank": 11,
      "name": "노시환",
      "team": "한화",
      "avg": 0.264,
      "games": 70,
      "pa": 317,
      "ab": 280,
      "hits": 74,
      "doubles": 13,
      "triples": 0,
      "hr": 15,
      "rbi": 50,
      "sb": 2,
      "bb": 29,
      "hbp": 5,
      "so": 89
    },
    {
      "rank": 12,
      "name": "최정",
      "team": "SSG",
      "avg": 0.303,
      "games": 64,
      "pa": 275,
      "ab": 228,
      "hits": 69,
      "doubles": 14,
      "triples": 1,
      "hr": 18,
      "rbi": 50,
      "sb": 3,
      "bb": 36,
      "hbp": 6,
      "so": 57
    },
    {
      "rank": 13,
      "name": "구자욱",
      "team": "삼성",
      "avg": 0.324,
      "games": 60,
      "pa": 258,
      "ab": 219,
      "hits": 71,
      "doubles": 14,
      "triples": 3,
      "hr": 7,
      "rbi": 50,
      "sb": 3,
      "bb": 32,
      "hbp": 3,
      "so": 37
    },
    {
      "rank": 14,
      "name": "문현빈",
      "team": "한화",
      "avg": 0.285,
      "games": 75,
      "pa": 343,
      "ab": 295,
      "hits": 84,
      "doubles": 20,
      "triples": 4,
      "hr": 9,
      "rbi": 48,
      "sb": 5,
      "bb": 40,
      "hbp": 4,
      "so": 39
    },
    {
      "rank": 15,
      "name": "박건우",
      "team": "NC",
      "avg": 0.286,
      "games": 74,
      "pa": 297,
      "ab": 252,
      "hits": 72,
      "doubles": 9,
      "triples": 0,
      "hr": 14,
      "rbi": 47,
      "sb": 5,
      "bb": 35,
      "hbp": 1,
      "so": 56
    },
    {
      "rank": 16,
      "name": "김호령",
      "team": "KIA",
      "avg": 0.286,
      "games": 79,
      "pa": 340,
      "ab": 308,
      "hits": 88,
      "doubles": 17,
      "triples": 1,
      "hr": 11,
      "rbi": 46,
      "sb": 8,
      "bb": 19,
      "hbp": 3,
      "so": 92
    },
    {
      "rank": 17,
      "name": "박민우",
      "team": "NC",
      "avg": 0.339,
      "games": 74,
      "pa": 312,
      "ab": 257,
      "hits": 87,
      "doubles": 17,
      "triples": 0,
      "hr": 4,
      "rbi": 45,
      "sb": 25,
      "bb": 45,
      "hbp": 6,
      "so": 36
    },
    {
      "rank": 18,
      "name": "최원준",
      "team": "KT",
      "avg": 0.365,
      "games": 75,
      "pa": 359,
      "ab": 307,
      "hits": 112,
      "doubles": 20,
      "triples": 3,
      "hr": 7,
      "rbi": 44,
      "sb": 16,
      "bb": 41,
      "hbp": 5,
      "so": 51
    },
    {
      "rank": 19,
      "name": "카메론",
      "team": "두산",
      "avg": 0.287,
      "games": 75,
      "pa": 314,
      "ab": 279,
      "hits": 80,
      "doubles": 19,
      "triples": 3,
      "hr": 9,
      "rbi": 43,
      "sb": 9,
      "bb": 30,
      "hbp": 3,
      "so": 53
    },
    {
      "rank": 20,
      "name": "류지혁",
      "team": "삼성",
      "avg": 0.295,
      "games": 75,
      "pa": 296,
      "ab": 251,
      "hits": 74,
      "doubles": 12,
      "triples": 4,
      "hr": 5,
      "rbi": 42,
      "sb": 15,
      "bb": 34,
      "hbp": 6,
      "so": 44
    },
    {
      "rank": 21,
      "name": "전민재",
      "team": "롯데",
      "avg": 0.281,
      "games": 75,
      "pa": 273,
      "ab": 249,
      "hits": 70,
      "doubles": 12,
      "triples": 0,
      "hr": 8,
      "rbi": 42,
      "sb": 8,
      "bb": 17,
      "hbp": 2,
      "so": 56
    },
    {
      "rank": 22,
      "name": "나성범",
      "team": "KIA",
      "avg": 0.285,
      "games": 76,
      "pa": 310,
      "ab": 267,
      "hits": 76,
      "doubles": 16,
      "triples": 0,
      "hr": 15,
      "rbi": 42,
      "sb": 0,
      "bb": 36,
      "hbp": 5,
      "so": 84
    },
    {
      "rank": 23,
      "name": "김재환",
      "team": "SSG",
      "avg": 0.22,
      "games": 69,
      "pa": 281,
      "ab": 232,
      "hits": 51,
      "doubles": 5,
      "triples": 0,
      "hr": 13,
      "rbi": 41,
      "sb": 1,
      "bb": 45,
      "hbp": 3,
      "so": 79
    },
    {
      "rank": 24,
      "name": "허인서",
      "team": "한화",
      "avg": 0.281,
      "games": 68,
      "pa": 223,
      "ab": 192,
      "hits": 54,
      "doubles": 4,
      "triples": 0,
      "hr": 11,
      "rbi": 40,
      "sb": 0,
      "bb": 21,
      "hbp": 5,
      "so": 67
    },
    {
      "rank": 25,
      "name": "데이비슨",
      "team": "NC",
      "avg": 0.29,
      "games": 63,
      "pa": 252,
      "ab": 221,
      "hits": 64,
      "doubles": 11,
      "triples": 1,
      "hr": 8,
      "rbi": 40,
      "sb": 1,
      "bb": 12,
      "hbp": 17,
      "so": 58
    },
    {
      "rank": 26,
      "name": "양의지",
      "team": "두산",
      "avg": 0.256,
      "games": 77,
      "pa": 303,
      "ab": 258,
      "hits": 66,
      "doubles": 8,
      "triples": 0,
      "hr": 11,
      "rbi": 39,
      "sb": 1,
      "bb": 23,
      "hbp": 15,
      "so": 33
    },
    {
      "rank": 27,
      "name": "오지환",
      "team": "LG",
      "avg": 0.242,
      "games": 74,
      "pa": 260,
      "ab": 223,
      "hits": 54,
      "doubles": 9,
      "triples": 0,
      "hr": 6,
      "rbi": 38,
      "sb": 2,
      "bb": 25,
      "hbp": 3,
      "so": 51
    },
    {
      "rank": 28,
      "name": "박재현",
      "team": "KIA",
      "avg": 0.279,
      "games": 76,
      "pa": 306,
      "ab": 283,
      "hits": 79,
      "doubles": 10,
      "triples": 2,
      "hr": 8,
      "rbi": 38,
      "sb": 15,
      "bb": 16,
      "hbp": 0,
      "so": 60
    },
    {
      "rank": 29,
      "name": "문보경",
      "team": "LG",
      "avg": 0.263,
      "games": 53,
      "pa": 219,
      "ab": 175,
      "hits": 46,
      "doubles": 4,
      "triples": 0,
      "hr": 7,
      "rbi": 37,
      "sb": 0,
      "bb": 38,
      "hbp": 1,
      "so": 38
    },
    {
      "rank": 30,
      "name": "최지훈",
      "team": "SSG",
      "avg": 0.231,
      "games": 77,
      "pa": 319,
      "ab": 290,
      "hits": 67,
      "doubles": 15,
      "triples": 6,
      "hr": 9,
      "rbi": 37,
      "sb": 8,
      "bb": 21,
      "hbp": 2,
      "so": 44
    }
  ],
  "sb": [
    {
      "rank": 1,
      "name": "황성빈",
      "team": "롯데",
      "avg": 0.294,
      "games": 59,
      "pa": 233,
      "ab": 211,
      "hits": 62,
      "doubles": 4,
      "triples": 6,
      "hr": 0,
      "rbi": 18,
      "sb": 30,
      "bb": 16,
      "hbp": 1,
      "so": 36
    },
    {
      "rank": 2,
      "name": "박민우",
      "team": "NC",
      "avg": 0.339,
      "games": 74,
      "pa": 312,
      "ab": 257,
      "hits": 87,
      "doubles": 17,
      "triples": 0,
      "hr": 4,
      "rbi": 45,
      "sb": 25,
      "bb": 45,
      "hbp": 6,
      "so": 36
    },
    {
      "rank": 3,
      "name": "박해민",
      "team": "LG",
      "avg": 0.296,
      "games": 79,
      "pa": 309,
      "ab": 257,
      "hits": 76,
      "doubles": 11,
      "triples": 0,
      "hr": 3,
      "rbi": 32,
      "sb": 22,
      "bb": 27,
      "hbp": 8,
      "so": 40
    },
    {
      "rank": 4,
      "name": "최정원",
      "team": "NC",
      "avg": 0.272,
      "games": 63,
      "pa": 134,
      "ab": 114,
      "hits": 31,
      "doubles": 3,
      "triples": 0,
      "hr": 0,
      "rbi": 6,
      "sb": 22,
      "bb": 9,
      "hbp": 5,
      "so": 25
    },
    {
      "rank": 5,
      "name": "김주원",
      "team": "NC",
      "avg": 0.312,
      "games": 76,
      "pa": 342,
      "ab": 298,
      "hits": 93,
      "doubles": 15,
      "triples": 0,
      "hr": 12,
      "rbi": 37,
      "sb": 20,
      "bb": 27,
      "hbp": 13,
      "so": 46
    },
    {
      "rank": 6,
      "name": "박찬호",
      "team": "두산",
      "avg": 0.274,
      "games": 80,
      "pa": 338,
      "ab": 296,
      "hits": 81,
      "doubles": 16,
      "triples": 2,
      "hr": 4,
      "rbi": 31,
      "sb": 18,
      "bb": 32,
      "hbp": 2,
      "so": 43
    },
    {
      "rank": 7,
      "name": "최원준",
      "team": "KT",
      "avg": 0.365,
      "games": 75,
      "pa": 359,
      "ab": 307,
      "hits": 112,
      "doubles": 20,
      "triples": 3,
      "hr": 7,
      "rbi": 44,
      "sb": 16,
      "bb": 41,
      "hbp": 5,
      "so": 51
    },
    {
      "rank": 8,
      "name": "심우준",
      "team": "한화",
      "avg": 0.262,
      "games": 69,
      "pa": 248,
      "ab": 214,
      "hits": 56,
      "doubles": 7,
      "triples": 0,
      "hr": 3,
      "rbi": 22,
      "sb": 15,
      "bb": 26,
      "hbp": 3,
      "so": 43
    },
    {
      "rank": 9,
      "name": "류지혁",
      "team": "삼성",
      "avg": 0.295,
      "games": 75,
      "pa": 296,
      "ab": 251,
      "hits": 74,
      "doubles": 12,
      "triples": 4,
      "hr": 5,
      "rbi": 42,
      "sb": 15,
      "bb": 34,
      "hbp": 6,
      "so": 44
    },
    {
      "rank": 10,
      "name": "박재현",
      "team": "KIA",
      "avg": 0.279,
      "games": 76,
      "pa": 306,
      "ab": 283,
      "hits": 79,
      "doubles": 10,
      "triples": 2,
      "hr": 8,
      "rbi": 38,
      "sb": 15,
      "bb": 16,
      "hbp": 0,
      "so": 60
    },
    {
      "rank": 11,
      "name": "장두성",
      "team": "롯데",
      "avg": 0.272,
      "games": 62,
      "pa": 159,
      "ab": 147,
      "hits": 40,
      "doubles": 4,
      "triples": 1,
      "hr": 0,
      "rbi": 13,
      "sb": 14,
      "bb": 7,
      "hbp": 2,
      "so": 36
    },
    {
      "rank": 12,
      "name": "김성윤",
      "team": "삼성",
      "avg": 0.296,
      "games": 61,
      "pa": 238,
      "ab": 206,
      "hits": 61,
      "doubles": 11,
      "triples": 2,
      "hr": 2,
      "rbi": 29,
      "sb": 13,
      "bb": 22,
      "hbp": 2,
      "so": 26
    },
    {
      "rank": 13,
      "name": "김지찬",
      "team": "삼성",
      "avg": 0.298,
      "games": 76,
      "pa": 290,
      "ab": 238,
      "hits": 71,
      "doubles": 5,
      "triples": 2,
      "hr": 0,
      "rbi": 21,
      "sb": 13,
      "bb": 40,
      "hbp": 3,
      "so": 18
    },
    {
      "rank": 14,
      "name": "정수빈",
      "team": "두산",
      "avg": 0.268,
      "games": 78,
      "pa": 310,
      "ab": 272,
      "hits": 73,
      "doubles": 6,
      "triples": 4,
      "hr": 5,
      "rbi": 29,
      "sb": 13,
      "bb": 29,
      "hbp": 3,
      "so": 43
    },
    {
      "rank": 15,
      "name": "정준재",
      "team": "SSG",
      "avg": 0.29,
      "games": 76,
      "pa": 309,
      "ab": 262,
      "hits": 76,
      "doubles": 8,
      "triples": 5,
      "hr": 1,
      "rbi": 27,
      "sb": 11,
      "bb": 27,
      "hbp": 3,
      "so": 40
    },
    {
      "rank": 16,
      "name": "신민재",
      "team": "LG",
      "avg": 0.238,
      "games": 78,
      "pa": 270,
      "ab": 231,
      "hits": 55,
      "doubles": 2,
      "triples": 0,
      "hr": 0,
      "rbi": 15,
      "sb": 10,
      "bb": 30,
      "hbp": 2,
      "so": 34
    },
    {
      "rank": 17,
      "name": "한태양",
      "team": "롯데",
      "avg": 0.245,
      "games": 35,
      "pa": 105,
      "ab": 94,
      "hits": 23,
      "doubles": 4,
      "triples": 0,
      "hr": 0,
      "rbi": 2,
      "sb": 9,
      "bb": 9,
      "hbp": 1,
      "so": 23
    },
    {
      "rank": 18,
      "name": "카메론",
      "team": "두산",
      "avg": 0.287,
      "games": 75,
      "pa": 314,
      "ab": 279,
      "hits": 80,
      "doubles": 19,
      "triples": 3,
      "hr": 9,
      "rbi": 43,
      "sb": 9,
      "bb": 30,
      "hbp": 3,
      "so": 53
    },
    {
      "rank": 19,
      "name": "최지훈",
      "team": "SSG",
      "avg": 0.231,
      "games": 77,
      "pa": 319,
      "ab": 290,
      "hits": 67,
      "doubles": 15,
      "triples": 6,
      "hr": 9,
      "rbi": 37,
      "sb": 8,
      "bb": 21,
      "hbp": 2,
      "so": 44
    },
    {
      "rank": 20,
      "name": "전민재",
      "team": "롯데",
      "avg": 0.281,
      "games": 75,
      "pa": 273,
      "ab": 249,
      "hits": 70,
      "doubles": 12,
      "triples": 0,
      "hr": 8,
      "rbi": 42,
      "sb": 8,
      "bb": 17,
      "hbp": 2,
      "so": 56
    },
    {
      "rank": 21,
      "name": "김호령",
      "team": "KIA",
      "avg": 0.286,
      "games": 79,
      "pa": 340,
      "ab": 308,
      "hits": 88,
      "doubles": 17,
      "triples": 1,
      "hr": 11,
      "rbi": 46,
      "sb": 8,
      "bb": 19,
      "hbp": 3,
      "so": 92
    },
    {
      "rank": 22,
      "name": "조수행",
      "team": "두산",
      "avg": 0.302,
      "games": 61,
      "pa": 76,
      "ab": 63,
      "hits": 19,
      "doubles": 2,
      "triples": 1,
      "hr": 0,
      "rbi": 8,
      "sb": 8,
      "bb": 7,
      "hbp": 0,
      "so": 8
    },
    {
      "rank": 23,
      "name": "페라자",
      "team": "한화",
      "avg": 0.315,
      "games": 77,
      "pa": 346,
      "ab": 286,
      "hits": 90,
      "doubles": 21,
      "triples": 1,
      "hr": 17,
      "rbi": 51,
      "sb": 7,
      "bb": 51,
      "hbp": 3,
      "so": 64
    },
    {
      "rank": 24,
      "name": "힐리어드",
      "team": "KT",
      "avg": 0.298,
      "games": 77,
      "pa": 345,
      "ab": 305,
      "hits": 91,
      "doubles": 14,
      "triples": 3,
      "hr": 19,
      "rbi": 68,
      "sb": 7,
      "bb": 36,
      "hbp": 0,
      "so": 92
    },
    {
      "rank": 25,
      "name": "김민규",
      "team": "KIA",
      "avg": 0.267,
      "games": 30,
      "pa": 31,
      "ab": 30,
      "hits": 8,
      "doubles": 3,
      "triples": 0,
      "hr": 0,
      "rbi": 4,
      "sb": 7,
      "bb": 1,
      "hbp": 0,
      "so": 11
    },
    {
      "rank": 26,
      "name": "오태곤",
      "team": "SSG",
      "avg": 0.23,
      "games": 69,
      "pa": 205,
      "ab": 187,
      "hits": 43,
      "doubles": 6,
      "triples": 0,
      "hr": 9,
      "rbi": 27,
      "sb": 6,
      "bb": 14,
      "hbp": 2,
      "so": 59
    },
    {
      "rank": 27,
      "name": "천성호",
      "team": "LG",
      "avg": 0.289,
      "games": 69,
      "pa": 204,
      "ab": 187,
      "hits": 54,
      "doubles": 13,
      "triples": 1,
      "hr": 1,
      "rbi": 25,
      "sb": 5,
      "bb": 12,
      "hbp": 3,
      "so": 28
    },
    {
      "rank": 28,
      "name": "문현빈",
      "team": "한화",
      "avg": 0.285,
      "games": 75,
      "pa": 343,
      "ab": 295,
      "hits": 84,
      "doubles": 20,
      "triples": 4,
      "hr": 9,
      "rbi": 48,
      "sb": 5,
      "bb": 40,
      "hbp": 4,
      "so": 39
    },
    {
      "rank": 29,
      "name": "박성한",
      "team": "SSG",
      "avg": 0.336,
      "games": 79,
      "pa": 347,
      "ab": 289,
      "hits": 97,
      "doubles": 18,
      "triples": 1,
      "hr": 3,
      "rbi": 36,
      "sb": 5,
      "bb": 55,
      "hbp": 1,
      "so": 37
    },
    {
      "rank": 30,
      "name": "안상현",
      "team": "SSG",
      "avg": 0.288,
      "games": 47,
      "pa": 123,
      "ab": 104,
      "hits": 30,
      "doubles": 5,
      "triples": 0,
      "hr": 1,
      "rbi": 10,
      "sb": 5,
      "bb": 14,
      "hbp": 2,
      "so": 24
    }
  ]
}