{
  "avg": [
    {
      "rank": 1,
      "name": "박성한",
      "team": "SSG",
      "avg": 0.47,
      "games": 18,
      "pa": 83,
      "ab": 66,
      "hits": 31,
      "doubles": 9,
      "triples": 1,
      "hr": 1,
      "rbi": 17,
      "sb": 3,
      "bb": 16,
      "hbp": 1,
      "so": 6
    },
    {
      "rank": 2,
      "name": "류지혁",
      "team": "삼성",
      "avg": 0.415,
      "games": 18,
      "pa": 78,
      "ab": 65,
      "hits": 27,
      "doubles": 7,
      "triples": 1,
      "hr": 2,
      "rbi": 13,
      "sb": 7,
      "bb": 13,
      "hbp": 0,
      "so": 8
    },
    {
      "rank": 3,
      "name": "천성호",
      "team": "LG",
      "avg": 0.391,
      "games": 17,
      "pa": 55,
      "ab": 46,
      "hits": 18,
      "doubles": 4,
      "triples": 0,
      "hr": 1,
      "rbi": 7,
      "sb": 3,
      "bb": 7,
      "hbp": 1,
      "so": 8
    },
    {
      "rank": 4,
      "name": "문현빈",
      "team": "한화",
      "avg": 0.382,
      "games": 17,
      "pa": 83,
      "ab": 68,
      "hits": 26,
      "doubles": 7,
      "triples": 1,
      "hr": 4,
      "rbi": 19,
      "sb": 1,
      "bb": 14,
      "hbp": 1,
      "so": 9
    },
    {
      "rank": 5,
      "name": "레이예스",
      "team": "롯데",
      "avg": 0.377,
      "games": 18,
      "pa": 80,
      "ab": 69,
      "hits": 26,
      "doubles": 3,
      "triples": 0,
      "hr": 5,
      "rbi": 12,
      "sb": 1,
      "bb": 9,
      "hbp": 1,
      "so": 11
    },
    {
      "rank": 6,
      "name": "페라자",
      "team": "한화",
      "avg": 0.375,
      "games": 18,
      "pa": 87,
      "ab": 72,
      "hits": 27,
      "doubles": 8,
      "triples": 0,
      "hr": 1,
      "rbi": 12,
      "sb": 3,
      "bb": 13,
      "hbp": 0,
      "so": 12
    },
    {
      "rank": 7,
      "name": "박준순",
      "team": "두산",
      "avg": 0.373,
      "games": 17,
      "pa": 69,
      "ab": 67,
      "hits": 25,
      "doubles": 3,
      "triples": 2,
      "hr": 3,
      "rbi": 13,
      "sb": 0,
      "bb": 1,
      "hbp": 1,
      "so": 19
    },
    {
      "rank": 8,
      "name": "안현민",
      "team": "KT",
      "avg": 0.365,
      "games": 14,
      "pa": 67,
      "ab": 52,
      "hits": 19,
      "doubles": 4,
      "triples": 1,
      "hr": 3,
      "rbi": 11,
      "sb": 1,
      "bb": 12,
      "hbp": 3,
      "so": 16
    },
    {
      "rank": 9,
      "name": "고명준",
      "team": "SSG",
      "avg": 0.365,
      "games": 17,
      "pa": 68,
      "ab": 63,
      "hits": 23,
      "doubles": 5,
      "triples": 0,
      "hr": 4,
      "rbi": 12,
      "sb": 1,
      "bb": 5,
      "hbp": 0,
      "so": 14
    },
    {
      "rank": 10,
      "name": "오스틴",
      "team": "LG",
      "avg": 0.347,
      "games": 18,
      "pa": 84,
      "ab": 72,
      "hits": 25,
      "doubles": 4,
      "triples": 1,
      "hr": 5,
      "rbi": 13,
      "sb": 0,
      "bb": 11,
      "hbp": 0,
      "so": 9
    },
    {
      "rank": 11,
      "name": "문성주",
      "team": "LG",
      "avg": 0.344,
      "games": 18,
      "pa": 73,
      "ab": 64,
      "hits": 22,
      "doubles": 3,
      "triples": 0,
      "hr": 0,
      "rbi": 8,
      "sb": 1,
      "bb": 5,
      "hbp": 2,
      "so": 8
    },
    {
      "rank": 12,
      "name": "박민우",
      "team": "NC",
      "avg": 0.344,
      "games": 17,
      "pa": 74,
      "ab": 64,
      "hits": 22,
      "doubles": 6,
      "triples": 0,
      "hr": 1,
      "rbi": 13,
      "sb": 9,
      "bb": 8,
      "hbp": 2,
      "so": 10
    },
    {
      "rank": 13,
      "name": "김선빈",
      "team": "KIA",
      "avg": 0.339,
      "games": 18,
      "pa": 76,
      "ab": 59,
      "hits": 20,
      "doubles": 4,
      "triples": 0,
      "hr": 1,
      "rbi": 12,
      "sb": 0,
      "bb": 15,
      "hbp": 1,
      "so": 5
    },
    {
      "rank": 14,
      "name": "박건우",
      "team": "NC",
      "avg": 0.333,
      "games": 18,
      "pa": 70,
      "ab": 60,
      "hits": 20,
      "doubles": 5,
      "triples": 0,
      "hr": 4,
      "rbi": 12,
      "sb": 2,
      "bb": 10,
      "hbp": 0,
      "so": 18
    },
    {
      "rank": 15,
      "name": "최원준",
      "team": "KT",
      "avg": 0.325,
      "games": 18,
      "pa": 89,
      "ab": 77,
      "hits": 25,
      "doubles": 8,
      "triples": 1,
      "hr": 0,
      "rbi": 10,
      "sb": 1,
      "bb": 11,
      "hbp": 0,
      "so": 14
    },
    {
      "rank": 16,
      "name": "디아즈",
      "team": "삼성",
      "avg": 0.314,
      "games": 18,
      "pa": 82,
      "ab": 70,
      "hits": 22,
      "doubles": 4,
      "triples": 0,
      "hr": 3,
      "rbi": 14,
      "sb": 0,
      "bb": 11,
      "hbp": 0,
      "so": 9
    },
    {
      "rank": 17,
      "name": "강백호",
      "team": "한화",
      "avg": 0.312,
      "games": 18,
      "pa": 85,
      "ab": 77,
      "hits": 24,
      "doubles": 5,
      "triples": 0,
      "hr": 4,
      "rbi": 22,
      "sb": 0,
      "bb": 7,
      "hbp": 0,
      "so": 14
    },
    {
      "rank": 18,
      "name": "김호령",
      "team": "KIA",
      "avg": 0.312,
      "games": 19,
      "pa": 88,
      "ab": 77,
      "hits": 24,
      "doubles": 7,
      "triples": 0,
      "hr": 1,
      "rbi": 9,
      "sb": 2,
      "bb": 5,
      "hbp": 3,
      "so": 15
    },
    {
      "rank": 19,
      "name": "데일",
      "team": "KIA",
      "avg": 0.309,
      "games": 18,
      "pa": 77,
      "ab": 68,
      "hits": 21,
      "doubles": 4,
      "triples": 0,
      "hr": 0,
      "rbi": 5,
      "sb": 1,
      "bb": 7,
      "hbp": 0,
      "so": 7
    },
    {
      "rank": 20,
      "name": "심우준",
      "team": "한화",
      "avg": 0.306,
      "games": 15,
      "pa": 57,
      "ab": 49,
      "hits": 15,
      "doubles": 4,
      "triples": 0,
      "hr": 2,
      "rbi": 10,
      "sb": 5,
      "bb": 7,
      "hbp": 1,
      "so": 13
    },
    {
      "rank": 21,
      "name": "노진혁",
      "team": "롯데",
      "avg": 0.305,
      "games": 18,
      "pa": 69,
      "ab": 59,
      "hits": 18,
      "doubles": 7,
      "triples": 0,
      "hr": 3,
      "rbi": 10,
      "sb": 0,
      "bb": 9,
      "hbp": 0,
      "so": 15
    },
    {
      "rank": 22,
      "name": "최형우",
      "team": "삼성",
      "avg": 0.297,
      "games": 18,
      "pa": 84,
      "ab": 64,
      "hits": 19,
      "doubles": 3,
      "triples": 0,
      "hr": 4,
      "rbi": 16,
      "sb": 0,
      "bb": 17,
      "hbp": 2,
      "so": 6
    },
    {
      "rank": 23,
      "name": "김현수",
      "team": "KT",
      "avg": 0.296,
      "games": 19,
      "pa": 89,
      "ab": 81,
      "hits": 24,
      "doubles": 6,
      "triples": 0,
      "hr": 2,
      "rbi": 17,
      "sb": 0,
      "bb": 8,
      "hbp": 0,
      "so": 11
    },
    {
      "rank": 24,
      "name": "최정원",
      "team": "NC",
      "avg": 0.295,
      "games": 17,
      "pa": 60,
      "ab": 44,
      "hits": 13,
      "doubles": 0,
      "triples": 0,
      "hr": 0,
      "rbi": 1,
      "sb": 7,
      "bb": 7,
      "hbp": 4,
      "so": 8
    },
    {
      "rank": 25,
      "name": "카스트로",
      "team": "KIA",
      "avg": 0.293,
      "games": 18,
      "pa": 79,
      "ab": 75,
      "hits": 22,
      "doubles": 9,
      "triples": 0,
      "hr": 2,
      "rbi": 16,
      "sb": 0,
      "bb": 3,
      "hbp": 0,
      "so": 19
    },
    {
      "rank": 26,
      "name": "오지환",
      "team": "LG",
      "avg": 0.293,
      "games": 17,
      "pa": 66,
      "ab": 58,
      "hits": 17,
      "doubles": 3,
      "triples": 0,
      "hr": 1,
      "rbi": 13,
      "sb": 1,
      "bb": 5,
      "hbp": 2,
      "so": 7
    },
    {
      "rank": 27,
      "name": "박찬혁",
      "team": "키움",
      "avg": 0.293,
      "games": 18,
      "pa": 63,
      "ab": 58,
      "hits": 17,
      "doubles": 1,
      "triples": 0,
      "hr": 0,
      "rbi": 3,
      "sb": 0,
      "bb": 3,
      "hbp": 1,
      "so": 14
    },
    {
      "rank": 28,
      "name": "최정",
      "team": "SSG",
      "avg": 0.292,
      "games": 18,
      "pa": 80,
      "ab": 65,
      "hits": 19,
      "doubles": 7,
      "triples": 0,
      "hr": 3,
      "rbi": 9,
      "sb": 2,
      "bb": 12,
      "hbp": 2,
      "so": 16
    },
    {
      "rank": 29,
      "name": "박찬호",
      "team": "두산",
      "avg": 0.29,
      "games": 19,
      "pa": 85,
      "ab": 69,
      "hits": 20,
      "doubles": 6,
      "triples": 0,
      "hr": 1,
      "rbi": 6,
      "sb": 6,
      "bb": 14,
      "hbp": 0,
      "so": 15
    },
    {
      "rank": 30,
      "name": "김휘집",
      "team": "NC",
      "avg": 0.288,
      "games": 16,
      "pa": 61,
      "ab": 52,
      "hits": 15,
      "doubles": 2,
      "triples": 0,
      "hr": 0,
      "rbi": 11,
      "sb": 1,
      "bb": 4,
      "hbp": 5,
      "so": 10
    }
  ],
  "hr": [
    {
      "rank": 1,
      "name": "장성우",
      "team": "KT",
      "avg": 0.273,
      "games": 19,
      "pa": 79,
      "ab": 66,
      "hits": 18,
      "doubles": 5,
      "triples": 0,
      "hr": 6,
      "rbi": 19,
      "sb": 0,
      "bb": 12,
      "hbp": 0,
      "so": 19
    },
    {
      "rank": 2,
      "name": "김도영",
      "team": "KIA",
      "avg": 0.243,
      "games": 19,
      "pa": 85,
      "ab": 70,
      "hits": 17,
      "doubles": 4,
      "triples": 0,
      "hr": 6,
      "rbi": 17,
      "sb": 1,
      "bb": 13,
      "hbp": 1,
      "so": 12
    },
    {
      "rank": 3,
      "name": "오스틴",
      "team": "LG",
      "avg": 0.347,
      "games": 18,
      "pa": 84,
      "ab": 72,
      "hits": 25,
      "doubles": 4,
      "triples": 1,
      "hr": 5,
      "rbi": 13,
      "sb": 0,
      "bb": 11,
      "hbp": 0,
      "so": 9
    },
    {
      "rank": 4,
      "name": "레이예스",
      "team": "롯데",
      "avg": 0.377,
      "games": 18,
      "pa": 80,
      "ab": 69,
      "hits": 26,
      "doubles": 3,
      "triples": 0,
      "hr": 5,
      "rbi": 12,
      "sb": 1,
      "bb": 9,
      "hbp": 1,
      "so": 11
    },
    {
      "rank": 5,
      "name": "강백호",
      "team": "한화",
      "avg": 0.312,
      "games": 18,
      "pa": 85,
      "ab": 77,
      "hits": 24,
      "doubles": 5,
      "triples": 0,
      "hr": 4,
      "rbi": 22,
      "sb": 0,
      "bb": 7,
      "hbp": 0,
      "so": 14
    },
    {
      "rank": 6,
      "name": "문현빈",
      "team": "한화",
      "avg": 0.382,
      "games": 17,
      "pa": 83,
      "ab": 68,
      "hits": 26,
      "doubles": 7,
      "triples": 1,
      "hr": 4,
      "rbi": 19,
      "sb": 1,
      "bb": 14,
      "hbp": 1,
      "so": 9
    },
    {
      "rank": 7,
      "name": "고명준",
      "team": "SSG",
      "avg": 0.365,
      "games": 17,
      "pa": 68,
      "ab": 63,
      "hits": 23,
      "doubles": 5,
      "triples": 0,
      "hr": 4,
      "rbi": 12,
      "sb": 1,
      "bb": 5,
      "hbp": 0,
      "so": 14
    },
    {
      "rank": 8,
      "name": "에레디아",
      "team": "SSG",
      "avg": 0.253,
      "games": 18,
      "pa": 80,
      "ab": 79,
      "hits": 20,
      "doubles": 1,
      "triples": 0,
      "hr": 4,
      "rbi": 13,
      "sb": 0,
      "bb": 1,
      "hbp": 0,
      "so": 18
    },
    {
      "rank": 9,
      "name": "최지훈",
      "team": "SSG",
      "avg": 0.203,
      "games": 18,
      "pa": 74,
      "ab": 64,
      "hits": 13,
      "doubles": 3,
      "triples": 0,
      "hr": 4,
      "rbi": 12,
      "sb": 3,
      "bb": 6,
      "hbp": 2,
      "so": 12
    },
    {
      "rank": 10,
      "name": "최형우",
      "team": "삼성",
      "avg": 0.297,
      "games": 18,
      "pa": 84,
      "ab": 64,
      "hits": 19,
      "doubles": 3,
      "triples": 0,
      "hr": 4,
      "rbi": 16,
      "sb": 0,
      "bb": 17,
      "hbp": 2,
      "so": 6
    },
    {
      "rank": 11,
      "name": "박건우",
      "team": "NC",
      "avg": 0.333,
      "games": 18,
      "pa": 70,
      "ab": 60,
      "hits": 20,
      "doubles": 5,
      "triples": 0,
      "hr": 4,
      "rbi": 12,
      "sb": 2,
      "bb": 10,
      "hbp": 0,
      "so": 18
    },
    {
      "rank": 12,
      "name": "카메론",
      "team": "두산",
      "avg": 0.24,
      "games": 19,
      "pa": 78,
      "ab": 75,
      "hits": 18,
      "doubles": 7,
      "triples": 1,
      "hr": 4,
      "rbi": 7,
      "sb": 1,
      "bb": 2,
      "hbp": 1,
      "so": 22
    },
    {
      "rank": 13,
      "name": "최정",
      "team": "SSG",
      "avg": 0.292,
      "games": 18,
      "pa": 80,
      "ab": 65,
      "hits": 19,
      "doubles": 7,
      "triples": 0,
      "hr": 3,
      "rbi": 9,
      "sb": 2,
      "bb": 12,
      "hbp": 2,
      "so": 16
    },
    {
      "rank": 14,
      "name": "디아즈",
      "team": "삼성",
      "avg": 0.314,
      "games": 18,
      "pa": 82,
      "ab": 70,
      "hits": 22,
      "doubles": 4,
      "triples": 0,
      "hr": 3,
      "rbi": 14,
      "sb": 0,
      "bb": 11,
      "hbp": 0,
      "so": 9
    },
    {
      "rank": 15,
      "name": "데이비슨",
      "team": "NC",
      "avg": 0.21,
      "games": 17,
      "pa": 70,
      "ab": 62,
      "hits": 13,
      "doubles": 3,
      "triples": 0,
      "hr": 3,
      "rbi": 9,
      "sb": 1,
      "bb": 5,
      "hbp": 3,
      "so": 15
    },
    {
      "rank": 16,
      "name": "이우성",
      "team": "NC",
      "avg": 0.265,
      "games": 16,
      "pa": 55,
      "ab": 49,
      "hits": 13,
      "doubles": 4,
      "triples": 0,
      "hr": 3,
      "rbi": 3,
      "sb": 0,
      "bb": 6,
      "hbp": 0,
      "so": 11
    },
    {
      "rank": 17,
      "name": "안현민",
      "team": "KT",
      "avg": 0.365,
      "games": 14,
      "pa": 67,
      "ab": 52,
      "hits": 19,
      "doubles": 4,
      "triples": 1,
      "hr": 3,
      "rbi": 11,
      "sb": 1,
      "bb": 12,
      "hbp": 3,
      "so": 16
    },
    {
      "rank": 18,
      "name": "힐리어드",
      "team": "KT",
      "avg": 0.192,
      "games": 19,
      "pa": 87,
      "ab": 73,
      "hits": 14,
      "doubles": 2,
      "triples": 1,
      "hr": 3,
      "rbi": 12,
      "sb": 2,
      "bb": 11,
      "hbp": 0,
      "so": 23
    },
    {
      "rank": 19,
      "name": "노진혁",
      "team": "롯데",
      "avg": 0.305,
      "games": 18,
      "pa": 69,
      "ab": 59,
      "hits": 18,
      "doubles": 7,
      "triples": 0,
      "hr": 3,
      "rbi": 10,
      "sb": 0,
      "bb": 9,
      "hbp": 0,
      "so": 15
    },
    {
      "rank": 20,
      "name": "윤동희",
      "team": "롯데",
      "avg": 0.19,
      "games": 17,
      "pa": 67,
      "ab": 63,
      "hits": 12,
      "doubles": 3,
      "triples": 0,
      "hr": 3,
      "rbi": 7,
      "sb": 0,
      "bb": 3,
      "hbp": 1,
      "so": 17
    },
    {
      "rank": 21,
      "name": "나성범",
      "team": "KIA",
      "avg": 0.25,
      "games": 17,
      "pa": 74,
      "ab": 64,
      "hits": 16,
      "doubles": 1,
      "triples": 0,
      "hr": 3,
      "rbi": 12,
      "sb": 0,
      "bb": 8,
      "hbp": 1,
      "so": 21
    },
    {
      "rank": 22,
      "name": "박준순",
      "team": "두산",
      "avg": 0.373,
      "games": 17,
      "pa": 69,
      "ab": 67,
      "hits": 25,
      "doubles": 3,
      "triples": 2,
      "hr": 3,
      "rbi": 13,
      "sb": 0,
      "bb": 1,
      "hbp": 1,
      "so": 19
    },
    {
      "rank": 23,
      "name": "문보경",
      "team": "LG",
      "avg": 0.273,
      "games": 17,
      "pa": 74,
      "ab": 55,
      "hits": 15,
      "doubles": 3,
      "triples": 0,
      "hr": 2,
      "rbi": 10,
      "sb": 0,
      "bb": 16,
      "hbp": 1,
      "so": 14
    },
    {
      "rank": 24,
      "name": "심우준",
      "team": "한화",
      "avg": 0.306,
      "games": 15,
      "pa": 57,
      "ab": 49,
      "hits": 15,
      "doubles": 4,
      "triples": 0,
      "hr": 2,
      "rbi": 10,
      "sb": 5,
      "bb": 7,
      "hbp": 1,
      "so": 13
    },
    {
      "rank": 25,
      "name": "채은성",
      "team": "한화",
      "avg": 0.243,
      "games": 18,
      "pa": 79,
      "ab": 70,
      "hits": 17,
      "doubles": 1,
      "triples": 0,
      "hr": 2,
      "rbi": 8,
      "sb": 1,
      "bb": 5,
      "hbp": 2,
      "so": 14
    },
    {
      "rank": 26,
      "name": "허인서",
      "team": "한화",
      "avg": 0.158,
      "games": 12,
      "pa": 25,
      "ab": 19,
      "hits": 3,
      "doubles": 0,
      "triples": 0,
      "hr": 2,
      "rbi": 6,
      "sb": 0,
      "bb": 4,
      "hbp": 1,
      "so": 10
    },
    {
      "rank": 27,
      "name": "김재환",
      "team": "SSG",
      "avg": 0.106,
      "games": 18,
      "pa": 82,
      "ab": 66,
      "hits": 7,
      "doubles": 0,
      "triples": 0,
      "hr": 2,
      "rbi": 9,
      "sb": 0,
      "bb": 15,
      "hbp": 0,
      "so": 20
    },
    {
      "rank": 28,
      "name": "구자욱",
      "team": "삼성",
      "avg": 0.292,
      "games": 13,
      "pa": 54,
      "ab": 48,
      "hits": 14,
      "doubles": 1,
      "triples": 1,
      "hr": 2,
      "rbi": 9,
      "sb": 0,
      "bb": 5,
      "hbp": 0,
      "so": 10
    },
    {
      "rank": 29,
      "name": "류지혁",
      "team": "삼성",
      "avg": 0.415,
      "games": 18,
      "pa": 78,
      "ab": 65,
      "hits": 27,
      "doubles": 7,
      "triples": 1,
      "hr": 2,
      "rbi": 13,
      "sb": 7,
      "bb": 13,
      "hbp": 0,
      "so": 8
    },
    {
      "rank": 30,
      "name": "김주원",
      "team": "NC",
      "avg": 0.183,
      "games": 18,
      "pa": 83,
      "ab": 71,
      "hits": 13,
      "doubles": 1,
      "triples": 0,
      "hr": 2,
      "rbi": 2,
      "sb": 3,
      "bb": 8,
      "hbp": 4,
      "so": 11
    }
  ],
  "rbi": [
    {
      "rank": 1,
      "name": "강백호",
      "team": "한화",
      "avg": 0.312,
      "games": 18,
      "pa": 85,
      "ab": 77,
      "hits": 24,
      "doubles": 5,
      "triples": 0,
      "hr": 4,
      "rbi": 22,
      "sb": 0,
      "bb": 7,
      "hbp": 0,
      "so": 14
    },
    {
      "rank": 2,
      "name": "문현빈",
      "team": "한화",
      "avg": 0.382,
      "games": 17,
      "pa": 83,
      "ab": 68,
      "hits": 26,
      "doubles": 7,
      "triples": 1,
      "hr": 4,
      "rbi": 19,
      "sb": 1,
      "bb": 14,
      "hbp": 1,
      "so": 9
    },
    {
      "rank": 3,
      "name": "장성우",
      "team": "KT",
      "avg": 0.273,
      "games": 19,
      "pa": 79,
      "ab": 66,
      "hits": 18,
      "doubles": 5,
      "triples": 0,
      "hr": 6,
      "rbi": 19,
      "sb": 0,
      "bb": 12,
      "hbp": 0,
      "so": 19
    },
    {
      "rank": 4,
      "name": "박성한",
      "team": "SSG",
      "avg": 0.47,
      "games": 18,
      "pa": 83,
      "ab": 66,
      "hits": 31,
      "doubles": 9,
      "triples": 1,
      "hr": 1,
      "rbi": 17,
      "sb": 3,
      "bb": 16,
      "hbp": 1,
      "so": 6
    },
    {
      "rank": 5,
      "name": "김현수",
      "team": "KT",
      "avg": 0.296,
      "games": 19,
      "pa": 89,
      "ab": 81,
      "hits": 24,
      "doubles": 6,
      "triples": 0,
      "hr": 2,
      "rbi": 17,
      "sb": 0,
      "bb": 8,
      "hbp": 0,
      "so": 11
    },
    {
      "rank": 6,
      "name": "김도영",
      "team": "KIA",
      "avg": 0.243,
      "games": 19,
      "pa": 85,
      "ab": 70,
      "hits": 17,
      "doubles": 4,
      "triples": 0,
      "hr": 6,
      "rbi": 17,
      "sb": 1,
      "bb": 13,
      "hbp": 1,
      "so": 12
    },
    {
      "rank": 7,
      "name": "최형우",
      "team": "삼성",
      "avg": 0.297,
      "games": 18,
      "pa": 84,
      "ab": 64,
      "hits": 19,
      "doubles": 3,
      "triples": 0,
      "hr": 4,
      "rbi": 16,
      "sb": 0,
      "bb": 17,
      "hbp": 2,
      "so": 6
    },
    {
      "rank": 8,
      "name": "카스트로",
      "team": "KIA",
      "avg": 0.293,
      "games": 18,
      "pa": 79,
      "ab": 75,
      "hits": 22,
      "doubles": 9,
      "triples": 0,
      "hr": 2,
      "rbi": 16,
      "sb": 0,
      "bb": 3,
      "hbp": 0,
      "so": 19
    },
    {
      "rank": 9,
      "name": "디아즈",
      "team": "삼성",
      "avg": 0.314,
      "games": 18,
      "pa": 82,
      "ab": 70,
      "hits": 22,
      "doubles": 4,
      "triples": 0,
      "hr": 3,
      "rbi": 14,
      "sb": 0,
      "bb": 11,
      "hbp": 0,
      "so": 9
    },
    {
      "rank": 10,
      "name": "오스틴",
      "team": "LG",
      "avg": 0.347,
      "games": 18,
      "pa": 84,
      "ab": 72,
      "hits": 25,
      "doubles": 4,
      "triples": 1,
      "hr": 5,
      "rbi": 13,
      "sb": 0,
      "bb": 11,
      "hbp": 0,
      "so": 9
    },
    {
      "rank": 11,
      "name": "오지환",
      "team": "LG",
      "avg": 0.293,
      "games": 17,
      "pa": 66,
      "ab": 58,
      "hits": 17,
      "doubles": 3,
      "triples": 0,
      "hr": 1,
      "rbi": 13,
      "sb": 1,
      "bb": 5,
      "hbp": 2,
      "so": 7
    },
    {
      "rank": 12,
      "name": "에레디아",
      "team": "SSG",
      "avg": 0.253,
      "games": 18,
      "pa": 80,
      "ab": 79,
      "hits": 20,
      "doubles": 1,
      "triples": 0,
      "hr": 4,
      "rbi": 13,
      "sb": 0,
      "bb": 1,
      "hbp": 0,
      "so": 18
    },
    {
      "rank": 13,
      "name": "류지혁",
      "team": "삼성",
      "avg": 0.415,
      "games": 18,
      "pa": 78,
      "ab": 65,
      "hits": 27,
      "doubles": 7,
      "triples": 1,
      "hr": 2,
      "rbi": 13,
      "sb": 7,
      "bb": 13,
      "hbp": 0,
      "so": 8
    },
    {
      "rank": 14,
      "name": "박민우",
      "team": "NC",
      "avg": 0.344,
      "games": 17,
      "pa": 74,
      "ab": 64,
      "hits": 22,
      "doubles": 6,
      "triples": 0,
      "hr": 1,
      "rbi": 13,
      "sb": 9,
      "bb": 8,
      "hbp": 2,
      "so": 10
    },
    {
      "rank": 15,
      "name": "박준순",
      "team": "두산",
      "avg": 0.373,
      "games": 17,
      "pa": 69,
      "ab": 67,
      "hits": 25,
      "doubles": 3,
      "triples": 2,
      "hr": 3,
      "rbi": 13,
      "sb": 0,
      "bb": 1,
      "hbp": 1,
      "so": 19
    },
    {
      "rank": 16,
      "name": "페라자",
      "team": "한화",
      "avg": 0.375,
      "games": 18,
      "pa": 87,
      "ab": 72,
      "hits": 27,
      "doubles": 8,
      "triples": 0,
      "hr": 1,
      "rbi": 12,
      "sb": 3,
      "bb": 13,
      "hbp": 0,
      "so": 12
    },
    {
      "rank": 17,
      "name": "고명준",
      "team": "SSG",
      "avg": 0.365,
      "games": 17,
      "pa": 68,
      "ab": 63,
      "hits": 23,
      "doubles": 5,
      "triples": 0,
      "hr": 4,
      "rbi": 12,
      "sb": 1,
      "bb": 5,
      "hbp": 0,
      "so": 14
    },
    {
      "rank": 18,
      "name": "최지훈",
      "team": "SSG",
      "avg": 0.203,
      "games": 18,
      "pa": 74,
      "ab": 64,
      "hits": 13,
      "doubles": 3,
      "triples": 0,
      "hr": 4,
      "rbi": 12,
      "sb": 3,
      "bb": 6,
      "hbp": 2,
      "so": 12
    },
    {
      "rank": 19,
      "name": "박건우",
      "team": "NC",
      "avg": 0.333,
      "games": 18,
      "pa": 70,
      "ab": 60,
      "hits": 20,
      "doubles": 5,
      "triples": 0,
      "hr": 4,
      "rbi": 12,
      "sb": 2,
      "bb": 10,
      "hbp": 0,
      "so": 18
    },
    {
      "rank": 20,
      "name": "힐리어드",
      "team": "KT",
      "avg": 0.192,
      "games": 19,
      "pa": 87,
      "ab": 73,
      "hits": 14,
      "doubles": 2,
      "triples": 1,
      "hr": 3,
      "rbi": 12,
      "sb": 2,
      "bb": 11,
      "hbp": 0,
      "so": 23
    },
    {
      "rank": 21,
      "name": "레이예스",
      "team": "롯데",
      "avg": 0.377,
      "games": 18,
      "pa": 80,
      "ab": 69,
      "hits": 26,
      "doubles": 3,
      "triples": 0,
      "hr": 5,
      "rbi": 12,
      "sb": 1,
      "bb": 9,
      "hbp": 1,
      "so": 11
    },
    {
      "rank": 22,
      "name": "김선빈",
      "team": "KIA",
      "avg": 0.339,
      "games": 18,
      "pa": 76,
      "ab": 59,
      "hits": 20,
      "doubles": 4,
      "triples": 0,
      "hr": 1,
      "rbi": 12,
      "sb": 0,
      "bb": 15,
      "hbp": 1,
      "so": 5
    },
    {
      "rank": 23,
      "name": "나성범",
      "team": "KIA",
      "avg": 0.25,
      "games": 17,
      "pa": 74,
      "ab": 64,
      "hits": 16,
      "doubles": 1,
      "triples": 0,
      "hr": 3,
      "rbi": 12,
      "sb": 0,
      "bb": 8,
      "hbp": 1,
      "so": 21
    },
    {
      "rank": 24,
      "name": "이주형",
      "team": "키움",
      "avg": 0.263,
      "games": 19,
      "pa": 88,
      "ab": 80,
      "hits": 21,
      "doubles": 7,
      "triples": 1,
      "hr": 2,
      "rbi": 12,
      "sb": 4,
      "bb": 5,
      "hbp": 3,
      "so": 16
    },
    {
      "rank": 25,
      "name": "박동원",
      "team": "LG",
      "avg": 0.24,
      "games": 17,
      "pa": 65,
      "ab": 50,
      "hits": 12,
      "doubles": 4,
      "triples": 0,
      "hr": 1,
      "rbi": 11,
      "sb": 0,
      "bb": 12,
      "hbp": 1,
      "so": 15
    },
    {
      "rank": 26,
      "name": "김휘집",
      "team": "NC",
      "avg": 0.288,
      "games": 16,
      "pa": 61,
      "ab": 52,
      "hits": 15,
      "doubles": 2,
      "triples": 0,
      "hr": 0,
      "rbi": 11,
      "sb": 1,
      "bb": 4,
      "hbp": 5,
      "so": 10
    },
    {
      "rank": 27,
      "name": "안현민",
      "team": "KT",
      "avg": 0.365,
      "games": 14,
      "pa": 67,
      "ab": 52,
      "hits": 19,
      "doubles": 4,
      "triples": 1,
      "hr": 3,
      "rbi": 11,
      "sb": 1,
      "bb": 12,
      "hbp": 3,
      "so": 16
    },
    {
      "rank": 28,
      "name": "문보경",
      "team": "LG",
      "avg": 0.273,
      "games": 17,
      "pa": 74,
      "ab": 55,
      "hits": 15,
      "doubles": 3,
      "triples": 0,
      "hr": 2,
      "rbi": 10,
      "sb": 0,
      "bb": 16,
      "hbp": 1,
      "so": 14
    },
    {
      "rank": 29,
      "name": "심우준",
      "team": "한화",
      "avg": 0.306,
      "games": 15,
      "pa": 57,
      "ab": 49,
      "hits": 15,
      "doubles": 4,
      "triples": 0,
      "hr": 2,
      "rbi": 10,
      "sb": 5,
      "bb": 7,
      "hbp": 1,
      "so": 13
    },
    {
      "rank": 30,
      "name": "전병우",
      "team": "삼성",
      "avg": 0.394,
      "games": 12,
      "pa": 40,
      "ab": 33,
      "hits": 13,
      "doubles": 2,
      "triples": 0,
      "hr": 1,
      "rbi": 10,
      "sb": 0,
      "bb": 3,
      "hbp": 4,
      "so": 7
    }
  ],
  "sb": [
    {
      "rank": 1,
      "name": "박민우",
      "team": "NC",
      "avg": 0.344,
      "games": 17,
      "pa": 74,
      "ab": 64,
      "hits": 22,
      "doubles": 6,
      "triples": 0,
      "hr": 1,
      "rbi": 13,
      "sb": 9,
      "bb": 8,
      "hbp": 2,
      "so": 10
    },
    {
      "rank": 2,
      "name": "류지혁",
      "team": "삼성",
      "avg": 0.415,
      "games": 18,
      "pa": 78,
      "ab": 65,
      "hits": 27,
      "doubles": 7,
      "triples": 1,
      "hr": 2,
      "rbi": 13,
      "sb": 7,
      "bb": 13,
      "hbp": 0,
      "so": 8
    },
    {
      "rank": 3,
      "name": "최정원",
      "team": "NC",
      "avg": 0.295,
      "games": 17,
      "pa": 60,
      "ab": 44,
      "hits": 13,
      "doubles": 0,
      "triples": 0,
      "hr": 0,
      "rbi": 1,
      "sb": 7,
      "bb": 7,
      "hbp": 4,
      "so": 8
    },
    {
      "rank": 4,
      "name": "박찬호",
      "team": "두산",
      "avg": 0.29,
      "games": 19,
      "pa": 85,
      "ab": 69,
      "hits": 20,
      "doubles": 6,
      "triples": 0,
      "hr": 1,
      "rbi": 6,
      "sb": 6,
      "bb": 14,
      "hbp": 0,
      "so": 15
    },
    {
      "rank": 5,
      "name": "심우준",
      "team": "한화",
      "avg": 0.306,
      "games": 15,
      "pa": 57,
      "ab": 49,
      "hits": 15,
      "doubles": 4,
      "triples": 0,
      "hr": 2,
      "rbi": 10,
      "sb": 5,
      "bb": 7,
      "hbp": 1,
      "so": 13
    },
    {
      "rank": 6,
      "name": "황성빈",
      "team": "롯데",
      "avg": 0.333,
      "games": 15,
      "pa": 49,
      "ab": 48,
      "hits": 16,
      "doubles": 1,
      "triples": 2,
      "hr": 0,
      "rbi": 2,
      "sb": 5,
      "bb": 0,
      "hbp": 0,
      "so": 8
    },
    {
      "rank": 7,
      "name": "박해민",
      "team": "LG",
      "avg": 0.262,
      "games": 18,
      "pa": 75,
      "ab": 65,
      "hits": 17,
      "doubles": 4,
      "triples": 0,
      "hr": 0,
      "rbi": 6,
      "sb": 4,
      "bb": 4,
      "hbp": 3,
      "so": 8
    },
    {
      "rank": 8,
      "name": "최원영",
      "team": "LG",
      "avg": 0.286,
      "games": 13,
      "pa": 8,
      "ab": 7,
      "hits": 2,
      "doubles": 1,
      "triples": 0,
      "hr": 0,
      "rbi": 1,
      "sb": 4,
      "bb": 0,
      "hbp": 0,
      "so": 1
    },
    {
      "rank": 9,
      "name": "허윤",
      "team": "NC",
      "avg": 0,
      "games": 12,
      "pa": 3,
      "ab": 3,
      "hits": 0,
      "doubles": 0,
      "triples": 0,
      "hr": 0,
      "rbi": 0,
      "sb": 4,
      "bb": 0,
      "hbp": 0,
      "so": 2
    },
    {
      "rank": 10,
      "name": "한태양",
      "team": "롯데",
      "avg": 0.265,
      "games": 17,
      "pa": 58,
      "ab": 49,
      "hits": 13,
      "doubles": 3,
      "triples": 0,
      "hr": 0,
      "rbi": 0,
      "sb": 4,
      "bb": 7,
      "hbp": 1,
      "so": 11
    },
    {
      "rank": 11,
      "name": "정수빈",
      "team": "두산",
      "avg": 0.19,
      "games": 19,
      "pa": 76,
      "ab": 63,
      "hits": 12,
      "doubles": 0,
      "triples": 0,
      "hr": 0,
      "rbi": 3,
      "sb": 4,
      "bb": 10,
      "hbp": 2,
      "so": 12
    },
    {
      "rank": 12,
      "name": "이주형",
      "team": "키움",
      "avg": 0.263,
      "games": 19,
      "pa": 88,
      "ab": 80,
      "hits": 21,
      "doubles": 7,
      "triples": 1,
      "hr": 2,
      "rbi": 12,
      "sb": 4,
      "bb": 5,
      "hbp": 3,
      "so": 16
    },
    {
      "rank": 13,
      "name": "신민재",
      "team": "LG",
      "avg": 0.161,
      "games": 18,
      "pa": 70,
      "ab": 62,
      "hits": 10,
      "doubles": 0,
      "triples": 0,
      "hr": 0,
      "rbi": 4,
      "sb": 3,
      "bb": 6,
      "hbp": 0,
      "so": 14
    },
    {
      "rank": 14,
      "name": "천성호",
      "team": "LG",
      "avg": 0.391,
      "games": 17,
      "pa": 55,
      "ab": 46,
      "hits": 18,
      "doubles": 4,
      "triples": 0,
      "hr": 1,
      "rbi": 7,
      "sb": 3,
      "bb": 7,
      "hbp": 1,
      "so": 8
    },
    {
      "rank": 15,
      "name": "페라자",
      "team": "한화",
      "avg": 0.375,
      "games": 18,
      "pa": 87,
      "ab": 72,
      "hits": 27,
      "doubles": 8,
      "triples": 0,
      "hr": 1,
      "rbi": 12,
      "sb": 3,
      "bb": 13,
      "hbp": 0,
      "so": 12
    },
    {
      "rank": 16,
      "name": "박성한",
      "team": "SSG",
      "avg": 0.47,
      "games": 18,
      "pa": 83,
      "ab": 66,
      "hits": 31,
      "doubles": 9,
      "triples": 1,
      "hr": 1,
      "rbi": 17,
      "sb": 3,
      "bb": 16,
      "hbp": 1,
      "so": 6
    },
    {
      "rank": 17,
      "name": "최지훈",
      "team": "SSG",
      "avg": 0.203,
      "games": 18,
      "pa": 74,
      "ab": 64,
      "hits": 13,
      "doubles": 3,
      "triples": 0,
      "hr": 4,
      "rbi": 12,
      "sb": 3,
      "bb": 6,
      "hbp": 2,
      "so": 12
    },
    {
      "rank": 18,
      "name": "김지찬",
      "team": "삼성",
      "avg": 0.25,
      "games": 18,
      "pa": 81,
      "ab": 64,
      "hits": 16,
      "doubles": 3,
      "triples": 1,
      "hr": 0,
      "rbi": 6,
      "sb": 3,
      "bb": 14,
      "hbp": 2,
      "so": 6
    },
    {
      "rank": 19,
      "name": "김주원",
      "team": "NC",
      "avg": 0.183,
      "games": 18,
      "pa": 83,
      "ab": 71,
      "hits": 13,
      "doubles": 1,
      "triples": 0,
      "hr": 2,
      "rbi": 2,
      "sb": 3,
      "bb": 8,
      "hbp": 4,
      "so": 11
    },
    {
      "rank": 20,
      "name": "홍창기",
      "team": "LG",
      "avg": 0.148,
      "games": 17,
      "pa": 72,
      "ab": 54,
      "hits": 8,
      "doubles": 2,
      "triples": 0,
      "hr": 0,
      "rbi": 3,
      "sb": 2,
      "bb": 15,
      "hbp": 3,
      "so": 16
    },
    {
      "rank": 21,
      "name": "오태곤",
      "team": "SSG",
      "avg": 0.25,
      "games": 14,
      "pa": 22,
      "ab": 20,
      "hits": 5,
      "doubles": 1,
      "triples": 0,
      "hr": 1,
      "rbi": 6,
      "sb": 2,
      "bb": 1,
      "hbp": 1,
      "so": 9
    },
    {
      "rank": 22,
      "name": "최정",
      "team": "SSG",
      "avg": 0.292,
      "games": 18,
      "pa": 80,
      "ab": 65,
      "hits": 19,
      "doubles": 7,
      "triples": 0,
      "hr": 3,
      "rbi": 9,
      "sb": 2,
      "bb": 12,
      "hbp": 2,
      "so": 16
    },
    {
      "rank": 23,
      "name": "박건우",
      "team": "NC",
      "avg": 0.333,
      "games": 18,
      "pa": 70,
      "ab": 60,
      "hits": 20,
      "doubles": 5,
      "triples": 0,
      "hr": 4,
      "rbi": 12,
      "sb": 2,
      "bb": 10,
      "hbp": 0,
      "so": 18
    },
    {
      "rank": 24,
      "name": "힐리어드",
      "team": "KT",
      "avg": 0.192,
      "games": 19,
      "pa": 87,
      "ab": 73,
      "hits": 14,
      "doubles": 2,
      "triples": 1,
      "hr": 3,
      "rbi": 12,
      "sb": 2,
      "bb": 11,
      "hbp": 0,
      "so": 23
    },
    {
      "rank": 25,
      "name": "김호령",
      "team": "KIA",
      "avg": 0.312,
      "games": 19,
      "pa": 88,
      "ab": 77,
      "hits": 24,
      "doubles": 7,
      "triples": 0,
      "hr": 1,
      "rbi": 9,
      "sb": 2,
      "bb": 5,
      "hbp": 3,
      "so": 15
    },
    {
      "rank": 26,
      "name": "박재현",
      "team": "KIA",
      "avg": 0.295,
      "games": 17,
      "pa": 50,
      "ab": 44,
      "hits": 13,
      "doubles": 2,
      "triples": 0,
      "hr": 0,
      "rbi": 6,
      "sb": 2,
      "bb": 3,
      "hbp": 0,
      "so": 9
    },
    {
      "rank": 27,
      "name": "문성주",
      "team": "LG",
      "avg": 0.344,
      "games": 18,
      "pa": 73,
      "ab": 64,
      "hits": 22,
      "doubles": 3,
      "triples": 0,
      "hr": 0,
      "rbi": 8,
      "sb": 1,
      "bb": 5,
      "hbp": 2,
      "so": 8
    },
    {
      "rank": 28,
      "name": "오지환",
      "team": "LG",
      "avg": 0.293,
      "games": 17,
      "pa": 66,
      "ab": 58,
      "hits": 17,
      "doubles": 3,
      "triples": 0,
      "hr": 1,
      "rbi": 13,
      "sb": 1,
      "bb": 5,
      "hbp": 2,
      "so": 7
    },
    {
      "rank": 29,
      "name": "문현빈",
      "team": "한화",
      "avg": 0.382,
      "games": 17,
      "pa": 83,
      "ab": 68,
      "hits": 26,
      "doubles": 7,
      "triples": 1,
      "hr": 4,
      "rbi": 19,
      "sb": 1,
      "bb": 14,
      "hbp": 1,
      "so": 9
    },
    {
      "rank": 30,
      "name": "이원석",
      "team": "한화",
      "avg": 0.406,
      "games": 9,
      "pa": 35,
      "ab": 32,
      "hits": 13,
      "doubles": 0,
      "triples": 2,
      "hr": 0,
      "rbi": 6,
      "sb": 1,
      "bb": 3,
      "hbp": 0,
      "so": 7
    }
  ]
}