[
  {
    "rank": 1,
    "team": "KT",
    "games": 38,
    "wins": 24,
    "losses": 13,
    "draws": 1,
    "winRate": 0.649,
    "gamesBehind": 0,
    "last10": "5승1무4패",
    "streak": "1승",
    "home": "12-0-7",
    "away": "12-1-6"
  },
  {
    "rank": 2,
    "team": "LG",
    "games": 38,
    "wins": 23,
    "losses": 15,
    "draws": 0,
    "winRate": 0.605,
    "gamesBehind": 1.5,
    "last10": "5승0무5패",
    "streak": "1승",
    "home": "14-0-8",
    "away": "9-0-7"
  },
  {
    "rank": 3,
    "team": "삼성",
    "games": 38,
    "wins": 22,
    "losses": 15,
    "draws": 1,
    "winRate": 0.595,
    "gamesBehind": 2,
    "last10": "8승0무2패",
    "streak": "1패",
    "home": "11-1-7",
    "away": "11-0-8"
  },
  {
    "rank": 4,
    "team": "SSG",
    "games": 38,
    "wins": 20,
    "losses": 17,
    "draws": 1,
    "winRate": 0.541,
    "gamesBehind": 4,
    "last10": "3승1무6패",
    "streak": "1패",
    "home": "9-1-9",
    "away": "11-0-8"
  },
  {
    "rank": 5,
    "team": "KIA",
    "games": 39,
    "wins": 18,
    "losses": 20,
    "draws": 1,
    "winRate": 0.474,
    "gamesBehind": 6.5,
    "last10": "5승0무5패",
    "streak": "1승",
    "home": "10-1-8",
    "away": "8-0-12"
  },
  {
    "rank": 5,
    "team": "두산",
    "games": 39,
    "wins": 18,
    "losses": 20,
    "draws": 1,
    "winRate": 0.474,
    "gamesBehind": 6.5,
    "last10": "5승0무5패",
    "streak": "1패",
    "home": "9-0-8",
    "away": "9-1-12"
  },
  {
    "rank": 7,
    "team": "한화",
    "games": 38,
    "wins": 17,
    "losses": 21,
    "draws": 0,
    "winRate": 0.447,
    "gamesBehind": 7.5,
    "last10": "6승0무4패",
    "streak": "1패",
    "home": "6-0-14",
    "away": "11-0-7"
  },
  {
    "rank": 8,
    "team": "NC",
    "games": 38,
    "wins": 16,
    "losses": 21,
    "draws": 1,
    "winRate": 0.432,
    "gamesBehind": 8,
    "last10": "3승1무6패",
    "streak": "1패",
    "home": "8-0-10",
    "away": "8-1-11"
  },
  {
    "rank": 9,
    "team": "롯데",
    "games": 37,
    "wins": 15,
    "losses": 21,
    "draws": 1,
    "winRate": 0.417,
    "gamesBehind": 8.5,
    "last10": "6승0무4패",
    "streak": "1승",
    "home": "6-0-12",
    "away": "9-1-9"
  },
  {
    "rank": 10,
    "team": "키움",
    "games": 39,
    "wins": 14,
    "losses": 24,
    "draws": 1,
    "winRate": 0.368,
    "gamesBehind": 10.5,
    "last10": "3승1무6패",
    "streak": "1승",
    "home": "10-1-9",
    "away": "4-0-15"
  }
]